storage_client/__init__.py
storage_client/client.py
storage_client/constants.py
storage_client-0.0.1.dist-info/licenses/LICENSE
storage_client-0.0.1.dist-info/METADATA
storage_client-0.0.1.dist-info/WHEEL
storage_client-0.0.1.dist-info/top_level.txt
storage_client-0.0.1.dist-info/RECORD
