Metadata-Version: 2.4
Name: storage-client
Version: 0.0.1
Summary: Python SDK for interacting with the Storage API
Author-email: Your Name <your@email.com>
License: MIT License
Requires-Python: >=3.8
License-File: LICENSE
Requires-Dist: requests>=2.25.0
Dynamic: license-file
